falcon_sugar/__init__.py
falcon_sugar/marshmallow.py
falcon_sugar/resource.cpython-36m-darwin.so
falcon_sugar/resource.py
falcon_sugar-0.3.1.dist-info/DESCRIPTION.rst
falcon_sugar-0.3.1.dist-info/METADATA
falcon_sugar-0.3.1.dist-info/RECORD
falcon_sugar-0.3.1.dist-info/WHEEL
falcon_sugar-0.3.1.dist-info/metadata.json
falcon_sugar-0.3.1.dist-info/top_level.txt
