Metadata-Version: 2.0
Name: falcon-sugar
Version: 0.3.1
Summary: A little sugar for Falcon.
Home-page: UNKNOWN
Author: UNKNOWN
Author-email: UNKNOWN
License: UNKNOWN
Platform: UNKNOWN
Requires-Python: >=3.5
Requires-Dist: falcon (<2,>=1.4)
Provides-Extra: marshmallow
Requires-Dist: marshmallow (==3.0.0b7); extra == 'marshmallow'
